{
  "schematic": true,
  "sex": false,
  "violence": false,
  "aac": false,
  "aacColor": false,
  "skin": false,
  "hair": false,
  "downloads": 0,
  "categories": [
    "expression",
    "meteorology",
    "atmospheric phenomena"
  ],
  "synsets": [
    "02775199-v",
    "02104910-v"
  ],
  "tags": [
    "communication",
    "language",
    "expression",
    "meteorology",
    "atmospheric phenomena"
  ],
  "_id": 10736,
  "created": "2009-11-20T21:09:07.000Z",
  "lastUpdated": "2021-07-19T11:50:56.522Z",
  "keywords": [
    {
      "type": 5,
      "keyword": "il y a du vent !",
      "hasLocution": false
    },
    {
      "type": 5,
      "keyword": "le vent souffle !",
      "hasLocution": false
    }
  ],
  "desc": ""
}