{
  "schematic": false,
  "sex": false,
  "violence": false,
  "aac": true,
  "aacColor": false,
  "skin": false,
  "hair": false,
  "downloads": 0,
  "categories": [
    "fruit",
    "core vocabulary-feeding"
  ],
  "synsets": [
    "07781049-n"
  ],
  "tags": [
    "feeding",
    "food",
    "plant-based food",
    "fruit",
    "core vocabulary"
  ],
  "_id": 11227,
  "created": "2009-12-24T12:23:22.000Z",
  "lastUpdated": "2021-07-19T12:37:07.257Z",
  "keywords": [
    {
      "type": 2,
      "keyword": "dattes",
      "hasLocution": true
    }
  ],
  "desc": ""
}