{
  "schematic": false,
  "sex": false,
  "violence": false,
  "aac": false,
  "aacColor": false,
  "skin": true,
  "hair": true,
  "downloads": 0,
  "categories": [
    "health personnel",
    "sanitary professional",
    "odontology"
  ],
  "synsets": [
    "10023944-n",
    "10023833-n"
  ],
  "tags": [
    "health",
    "medicine",
    "professional",
    "work",
    "odontology"
  ],
  "_id": 11229,
  "created": "2009-12-24T12:32:09.000Z",
  "lastUpdated": "2021-07-19T12:37:29.544Z",
  "keywords": [
    {
      "type": 2,
      "keyword": "dentiste",
      "hasLocution": true,
      "plural": "dentistes"
    },
    {
      "type": 2,
      "keyword": "odontologiste",
      "hasLocution": true,
      "plural": "odontologistes"
    }
  ],
  "desc": ""
}