{
  "schematic": false,
  "sex": false,
  "violence": false,
  "aac": false,
  "aacColor": false,
  "skin": true,
  "hair": true,
  "downloads": 0,
  "categories": [
    "musical artist",
    "professional artist",
    "musical notation"
  ],
  "synsets": [
    "09972018-n"
  ],
  "tags": [
    "work",
    "professional",
    "artist",
    "music",
    "visual art",
    "musical notation",
    "musical composition"
  ],
  "_id": 11240,
  "created": "2009-12-24T13:00:22.000Z",
  "lastUpdated": "2021-07-19T12:47:22.474Z",
  "keywords": [
    {
      "type": 2,
      "keyword": "chef d'orchestre",
      "hasLocution": true,
      "plural": "chefs d'orchestre"
    }
  ],
  "desc": ""
}