{
  "schematic": false,
  "sex": false,
  "violence": false,
  "aac": false,
  "aacColor": false,
  "skin": false,
  "hair": false,
  "downloads": 0,
  "categories": [
    "group"
  ],
  "synsets": [
    "08024893-n",
    "08181484-n",
    "08066153-n"
  ],
  "tags": [
    "person",
    "group"
  ],
  "_id": 12333,
  "created": "2010-02-09T16:51:50.000Z",
  "lastUpdated": "2021-07-20T08:06:51.231Z",
  "keywords": [
    {
      "type": 2,
      "keyword": "organisation",
      "hasLocution": true
    },
    {
      "type": 2,
      "keyword": "association",
      "hasLocution": true
    }
  ],
  "desc": ""
}