{
  "schematic": false,
  "sex": false,
  "violence": false,
  "aac": false,
  "aacColor": false,
  "skin": true,
  "hair": true,
  "downloads": 0,
  "categories": [
    "verb",
    "marital status"
  ],
  "synsets": [
    "02496283-v"
  ],
  "tags": [
    "communication",
    "language",
    "verb",
    "person",
    "marital status"
  ],
  "_id": 15008,
  "created": "2010-03-27T18:35:54.000Z",
  "lastUpdated": "2021-07-20T08:58:20.560Z",
  "keywords": [
    {
      "type": 3,
      "keyword": "divorcer",
      "hasLocution": false
    }
  ],
  "desc": ""
}