{
  "schematic": false,
  "sex": false,
  "violence": false,
  "aac": false,
  "aacColor": false,
  "skin": true,
  "hair": true,
  "downloads": 0,
  "categories": [
    "educational space",
    "students",
    "signaling system"
  ],
  "synsets": [
    "10541628-n",
    "04112987-n"
  ],
  "tags": [
    "education",
    "educational space",
    "students",
    "communication",
    "signaling system"
  ],
  "_id": 16190,
  "created": "2010-04-18T22:27:15.000Z",
  "lastUpdated": "2021-07-21T07:10:47.867Z",
  "keywords": [
    {
      "type": 2,
      "keyword": "bureau des représentants",
      "hasLocution": false
    },
    {
      "keyword": "bureau des délégués",
      "hasLocution": false
    }
  ],
  "desc": ""
}