{
  "schematic": false,
  "sex": false,
  "violence": false,
  "aac": false,
  "aacColor": false,
  "skin": true,
  "hair": true,
  "downloads": 0,
  "categories": [
    "service building",
    "professional",
    "work organization"
  ],
  "synsets": [
    "08371279-n"
  ],
  "tags": [
    "place",
    "building",
    "service building",
    "work",
    "professional",
    "organization"
  ],
  "_id": 24637,
  "created": "2011-02-08T17:08:03.000Z",
  "lastUpdated": "2021-07-30T01:34:48.924Z",
  "keywords": [
    {
      "type": 2,
      "hasLocution": false,
      "keyword": "pôle emploi",
      "plural": "pôles emploi"
    },
    {
      "hasLocution": false,
      "type": 2,
      "keyword": "agence de recrutement",
      "plural": "agences de recrutement"
    },
    {
      "keyword": "agence d'interim",
      "hasLocution": false,
      "type": 2,
      "plural": "agences d'interim"
    }
  ],
  "desc": ""
}