{
  "schematic": false,
  "sex": false,
  "violence": false,
  "aac": false,
  "aacColor": false,
  "skin": false,
  "hair": false,
  "downloads": 0,
  "categories": [
    "viviparous",
    "qualifying adjective"
  ],
  "synsets": [
    "02529085-a"
  ],
  "tags": [
    "animal",
    "viviparous",
    "communication",
    "language",
    "adjective",
    "qualifying adjective"
  ],
  "_id": 25528,
  "created": "2011-08-16T18:50:02.000Z",
  "lastUpdated": "2024-10-21T12:04:02.552Z",
  "keywords": [
    {
      "type": 4,
      "keyword": "vivipare",
      "hasLocution": false,
      "plural": "vivipares"
    }
  ],
  "desc": ""
}