{
  "schematic": false,
  "sex": false,
  "violence": false,
  "aac": false,
  "aacColor": false,
  "skin": false,
  "hair": false,
  "downloads": 0,
  "categories": [
    "hospitality industry"
  ],
  "synsets": [],
  "tags": [
    "work",
    "tertiary sector",
    "hospitality industry"
  ],
  "_id": 25706,
  "created": "2011-08-26T12:04:57.000Z",
  "lastUpdated": "2021-07-30T08:18:03.225Z",
  "keywords": [
    {
      "type": 2,
      "keyword": "demi-pension",
      "hasLocution": false,
      "plural": "demi-pensions"
    }
  ],
  "desc": ""
}