{
  "schematic": false,
  "sex": false,
  "violence": false,
  "aac": false,
  "aacColor": false,
  "skin": true,
  "hair": true,
  "downloads": 0,
  "categories": [
    "cattle farming",
    "professional"
  ],
  "synsets": [
    "10607013-n"
  ],
  "tags": [
    "work",
    "primary sector",
    "cattle farming",
    "professional"
  ],
  "_id": 27535,
  "created": "2013-01-17T18:20:19.000Z",
  "lastUpdated": "2021-07-29T06:36:46.616Z",
  "keywords": [
    {
      "type": 2,
      "keyword": "berger",
      "hasLocution": true,
      "plural": "bergers"
    }
  ],
  "desc": ""
}