{
  "schematic": false,
  "sex": false,
  "violence": false,
  "aac": false,
  "aacColor": false,
  "skin": false,
  "hair": false,
  "downloads": 0,
  "categories": [
    "accessories"
  ],
  "synsets": [
    "03265722-n"
  ],
  "tags": [
    "object",
    "fashion",
    "accessories"
  ],
  "_id": 27929,
  "created": "2013-03-04T12:34:42.000Z",
  "lastUpdated": "2021-07-28T08:06:34.417Z",
  "keywords": [
    {
      "type": 2,
      "keyword": "oreillettes",
      "hasLocution": false
    }
  ],
  "desc": ""
}