{
  "schematic": false,
  "sex": false,
  "violence": false,
  "aac": false,
  "aacColor": false,
  "skin": false,
  "hair": false,
  "downloads": 0,
  "categories": [
    "traditional dish"
  ],
  "synsets": [
    "07884316-n"
  ],
  "tags": [
    "feeding",
    "food",
    "gastronomy",
    "traditional dish"
  ],
  "_id": 28923,
  "created": "2013-06-23T15:58:19.000Z",
  "lastUpdated": "2021-07-27T10:35:13.563Z",
  "keywords": [
    {
      "type": 2,
      "keyword": "riz cantonais",
      "hasLocution": false
    }
  ],
  "desc": ""
}