{
  "schematic": false,
  "sex": false,
  "violence": false,
  "aac": false,
  "aacColor": false,
  "skin": false,
  "hair": false,
  "downloads": 0,
  "categories": [
    "cleaning product"
  ],
  "synsets": [
    "04374567-n"
  ],
  "tags": [
    "object",
    "cleaning product"
  ],
  "_id": 2908,
  "created": "2008-01-15T11:38:44.000Z",
  "lastUpdated": "2021-03-21T11:37:43.180Z",
  "keywords": [
    {
      "type": 2,
      "hasLocution": false,
      "keyword": "balai à franges",
      "plural": "balai à franges"
    },
    {
      "keyword": "serpillère",
      "plural": "serpillères",
      "hasLocution": false,
      "type": 2
    }
  ],
  "desc": ""
}