{
  "schematic": false,
  "sex": false,
  "violence": false,
  "aac": false,
  "aacColor": false,
  "skin": false,
  "hair": false,
  "downloads": 0,
  "categories": [
    "number",
    "numeral adjective"
  ],
  "synsets": [
    "13603216-n",
    "06820056-n",
    "02199631-s"
  ],
  "tags": [
    "communication",
    "language",
    "alphabet",
    "number",
    "mathematics",
    "adjective",
    "numeral adjective"
  ],
  "_id": 29360,
  "created": "2013-06-30T21:43:16.000Z",
  "lastUpdated": "2024-10-20T09:33:51.051Z",
  "keywords": [
    {
      "keyword": "58",
      "hasLocution": false,
      "type": 4
    },
    {
      "type": 4,
      "keyword": "cinquante-huit",
      "hasLocution": false
    }
  ],
  "desc": ""
}