{
  "schematic": false,
  "sex": false,
  "violence": false,
  "aac": false,
  "aacColor": false,
  "skin": false,
  "hair": false,
  "downloads": 0,
  "categories": [
    "animal material",
    "clothing industry"
  ],
  "synsets": [
    "15128784-n"
  ],
  "tags": [
    "material",
    "raw material",
    "animal material",
    "work",
    "secondary sector",
    "clothing industry"
  ],
  "_id": 2948,
  "created": "2008-01-15T13:31:19.000Z",
  "lastUpdated": "2021-03-20T14:57:47.252Z",
  "keywords": [
    {
      "type": 2,
      "keyword": "laine",
      "hasLocution": true,
      "plural": "laines"
    }
  ],
  "desc": ""
}