{
  "schematic": true,
  "sex": false,
  "violence": false,
  "aac": false,
  "aacColor": false,
  "skin": false,
  "hair": false,
  "downloads": 0,
  "categories": [
    "day hours"
  ],
  "synsets": [
    "15259739-n"
  ],
  "tags": [
    "time",
    "unit of time",
    "day hours"
  ],
  "_id": 29526,
  "created": "2013-07-02T19:47:43.000Z",
  "lastUpdated": "2021-08-02T21:51:50.159Z",
  "keywords": [
    {
      "keyword": "midi moins le quart",
      "hasLocution": false,
      "type": 6
    },
    {
      "keyword": "minuit moins le quart",
      "hasLocution": false,
      "type": 6
    },
    {
      "keyword": "11h45",
      "hasLocution": false,
      "type": 6
    },
    {
      "keyword": "23h45",
      "hasLocution": false,
      "type": 6
    },
    {
      "keyword": "onze heures quarante-cinq",
      "hasLocution": false,
      "type": 6
    },
    {
      "keyword": "vingt-trois heures quarante-cinq",
      "hasLocution": false,
      "type": 6
    },
    {
      "keyword": "11:45",
      "hasLocution": false,
      "type": 6
    },
    {
      "keyword": "23:45",
      "hasLocution": false,
      "type": 6
    }
  ],
  "desc": ""
}