{
  "schematic": false,
  "sex": false,
  "violence": false,
  "aac": false,
  "aacColor": false,
  "skin": false,
  "hair": false,
  "downloads": 0,
  "categories": [
    "commercial building",
    "clothes"
  ],
  "synsets": [
    "03653380-n"
  ],
  "tags": [
    "place",
    "building",
    "trade",
    "object",
    "fashion",
    "clothes"
  ],
  "_id": 29841,
  "created": "2013-11-26T13:46:19.000Z",
  "lastUpdated": "2021-07-28T16:30:31.127Z",
  "keywords": [
    {
      "type": 2,
      "keyword": "blanchisserie",
      "hasLocution": true,
      "plural": "blanchisseries"
    },
    {
      "keyword": "laverie",
      "hasLocution": false,
      "type": 2,
      "plural": "laveries"
    }
  ],
  "desc": ""
}