{
  "schematic": false,
  "sex": false,
  "violence": false,
  "aac": false,
  "aacColor": false,
  "skin": false,
  "hair": false,
  "downloads": 0,
  "categories": [
    "letter",
    "conjunction",
    "disjunctive conjunction"
  ],
  "synsets": [
    "06841868-n",
    "06831828-n",
    "06837277-n",
    "01470615-a"
  ],
  "tags": [
    "communication",
    "language",
    "alphabet",
    "letter",
    "conjunction",
    "copulative conjunction",
    "disjunctive conjunction"
  ],
  "_id": 3136,
  "created": "2008-01-24T14:01:25.000Z",
  "lastUpdated": "2024-11-19T06:18:29.207Z",
  "keywords": [
    {
      "type": 6,
      "keyword": "O",
      "hasLocution": true
    }
  ],
  "desc": ""
}