{
  "schematic": false,
  "sex": false,
  "violence": false,
  "aac": false,
  "aacColor": false,
  "skin": true,
  "hair": true,
  "downloads": 0,
  "categories": [
    "verb",
    "educational task",
    "literature"
  ],
  "synsets": [
    "00626756-v"
  ],
  "tags": [
    "communication",
    "language",
    "verb",
    "education",
    "educational task",
    "literature"
  ],
  "_id": 31680,
  "created": "2017-12-01T11:56:01.000Z",
  "lastUpdated": "2021-07-24T16:13:47.737Z",
  "keywords": [
    {
      "type": 3,
      "meaning": "tr. Reconnaître les signes graphiques d'une langue, former mentalement ou à voix haute les sons que ces signes ou leurs combinaisons représentent et leur associer un sens",
      "keyword": "lire",
      "hasLocution": true
    }
  ],
  "desc": ""
}