{
  "schematic": false,
  "sex": false,
  "violence": false,
  "aac": false,
  "aacColor": false,
  "skin": true,
  "hair": true,
  "downloads": 0,
  "categories": [
    "educational organization"
  ],
  "synsets": [
    "06711015-n",
    "08426574-n"
  ],
  "tags": [
    "education",
    "organization"
  ],
  "_id": 31997,
  "created": "2017-12-04T20:31:37.000Z",
  "lastUpdated": "2021-07-26T12:58:46.125Z",
  "keywords": [
    {
      "keyword": "baccalauréat",
      "hasLocution": false,
      "plural": "baccalauréats",
      "type": 2
    },
    {
      "hasLocution": true,
      "keyword": "lycée",
      "plural": "lycées",
      "type": 2
    },
    {
      "keyword": "enseignement secondaire",
      "hasLocution": false,
      "plural": "enseignements secondaires",
      "type": 2
    }
  ],
  "desc": ""
}