{
  "schematic": false,
  "sex": false,
  "violence": false,
  "aac": false,
  "aacColor": false,
  "skin": true,
  "hair": true,
  "downloads": 0,
  "categories": [
    "professional",
    "baking"
  ],
  "synsets": [
    "09852896-n",
    "09853011-n"
  ],
  "tags": [
    "work",
    "professional",
    "feeding",
    "food",
    "ultra-processed food",
    "dessert",
    "baking"
  ],
  "_id": 3358,
  "created": "2008-02-01T13:56:49.000Z",
  "lastUpdated": "2021-04-06T17:16:18.261Z",
  "keywords": [
    {
      "type": 2,
      "keyword": "boulanger",
      "hasLocution": true,
      "plural": "boulangers"
    },
    {
      "keyword": "fabricant de pain",
      "hasLocution": false,
      "plural": "fabricants de pain",
      "type": 2
    }
  ],
  "desc": ""
}