{
  "schematic": false,
  "sex": false,
  "violence": false,
  "aac": false,
  "aacColor": false,
  "skin": false,
  "hair": false,
  "downloads": 0,
  "categories": [
    "orthographic sign"
  ],
  "synsets": [
    "06830640-n"
  ],
  "tags": [
    "communication",
    "language",
    "alphabet",
    "orthographic sign"
  ],
  "_id": 34629,
  "created": "2019-03-06T13:29:08.000Z",
  "lastUpdated": "2021-07-16T15:31:41.141Z",
  "keywords": [
    {
      "keyword": "ponctuation",
      "hasLocution": false,
      "plural": "ponctuations",
      "type": 2
    },
    {
      "keyword": "signes de ponctuation",
      "hasLocution": false,
      "plural": "signes de ponctuation",
      "type": 2
    }
  ],
  "desc": ""
}