{
  "schematic": false,
  "sex": false,
  "violence": false,
  "aac": false,
  "aacColor": false,
  "skin": true,
  "hair": false,
  "downloads": 0,
  "categories": [
    "verb",
    "clothes",
    "routine"
  ],
  "synsets": [
    "01356373-v"
  ],
  "tags": [
    "communication",
    "language",
    "verb",
    "object",
    "fashion",
    "clothes",
    "person",
    "routine"
  ],
  "_id": 37430,
  "keywords": [
    {
      "keyword": "monter la fermeture-éclair",
      "hasLocution": false,
      "type": 3
    },
    {
      "keyword": "zipper",
      "hasLocution": false,
      "type": 3
    },
    {
      "keyword": "mettre la fermeture-éclair",
      "hasLocution": false,
      "type": 3
    },
    {
      "keyword": "remonter la fermeture-éclair",
      "hasLocution": false,
      "type": 3
    }
  ],
  "created": "2021-03-04T18:26:03.682Z",
  "lastUpdated": "2021-03-14T14:54:57.470Z"
}