{
  "schematic": true,
  "sex": false,
  "violence": false,
  "aac": false,
  "aacColor": false,
  "skin": true,
  "hair": false,
  "downloads": 0,
  "categories": [
    "verb",
    "senses"
  ],
  "synsets": [
    "01212242-v",
    "02163627-v"
  ],
  "tags": [
    "communication",
    "language",
    "verb",
    "human body",
    "physiology",
    "human physiology",
    "senses"
  ],
  "_id": 37719,
  "keywords": [
    {
      "keyword": "sentir",
      "hasLocution": true,
      "type": 3
    },
    {
      "keyword": "toucher",
      "hasLocution": true,
      "type": 3
    },
    {
      "keyword": "s'orienter",
      "hasLocution": true,
      "type": 3
    }
  ],
  "created": "2021-08-21T10:11:20.433Z",
  "lastUpdated": "2021-08-22T21:32:32.991Z"
}