{
  "schematic": true,
  "sex": false,
  "violence": false,
  "aac": false,
  "aacColor": false,
  "skin": false,
  "hair": false,
  "downloads": 0,
  "categories": [
    "unit of time"
  ],
  "synsets": [
    "07324217-n",
    "00066148-r"
  ],
  "tags": [
    "time",
    "unit of time"
  ],
  "_id": 37744,
  "keywords": [
    {
      "keyword": "dernière fois",
      "hasLocution": false,
      "plural": "dernières fois",
      "type": 4
    }
  ],
  "created": "2021-09-02T11:13:03.062Z",
  "lastUpdated": "2021-09-03T15:44:33.324Z"
}