{
  "schematic": false,
  "sex": false,
  "violence": false,
  "aac": false,
  "aacColor": false,
  "skin": true,
  "hair": true,
  "downloads": 0,
  "categories": [
    "professional",
    "circus"
  ],
  "synsets": [
    "10135603-n"
  ],
  "tags": [
    "work",
    "professional",
    "scenic art",
    "circus",
    "show"
  ],
  "_id": 4641,
  "created": "2008-04-29T13:27:58.000Z",
  "lastUpdated": "2021-04-12T21:33:41.335Z",
  "keywords": [
    {
      "type": 2,
      "keyword": "équilibriste",
      "hasLocution": true,
      "plural": "équilibristes"
    },
    {
      "keyword": "funambule",
      "hasLocution": false,
      "plural": "funambules",
      "type": 2
    }
  ],
  "desc": ""
}