{
  "schematic": false,
  "sex": false,
  "violence": false,
  "aac": false,
  "aacColor": false,
  "skin": false,
  "hair": false,
  "downloads": 0,
  "categories": [
    "plant anatomy"
  ],
  "synsets": [
    "13173519-n",
    "15261656-n"
  ],
  "tags": [
    "plant",
    "plant anatomy",
    "anatomy"
  ],
  "_id": 5076,
  "created": "2008-07-04T12:48:23.000Z",
  "lastUpdated": "2021-07-14T20:23:23.696Z",
  "keywords": [
    {
      "type": 2,
      "keyword": "feuille",
      "hasLocution": true,
      "plural": "feuilles"
    },
    {
      "type": 2,
      "keyword": "feuille marron",
      "hasLocution": true,
      "plural": "feuilles marrons"
    },
    {
      "type": 2,
      "keyword": "feuille d'automne",
      "hasLocution": false,
      "plural": "feuilles d'automne"
    }
  ],
  "desc": ""
}