{
  "schematic": true,
  "sex": false,
  "violence": false,
  "aac": false,
  "aacColor": false,
  "skin": false,
  "hair": false,
  "downloads": 0,
  "categories": [
    "orthographic sign"
  ],
  "synsets": [
    "06819327-n"
  ],
  "tags": [
    "communication",
    "language",
    "alphabet",
    "orthographic sign"
  ],
  "_id": 5095,
  "created": "2008-07-04T13:14:16.000Z",
  "lastUpdated": "2021-04-10T21:16:14.325Z",
  "keywords": [
    {
      "type": 2,
      "keyword": "dièse",
      "hasLocution": true,
      "plural": "dièses"
    },
    {
      "keyword": "#",
      "hasLocution": false,
      "type": 6
    },
    {
      "keyword": "hashtag",
      "hasLocution": false,
      "plural": "hashtags",
      "type": 2
    }
  ],
  "desc": ""
}