{
  "schematic": false,
  "sex": false,
  "violence": false,
  "aac": false,
  "aacColor": false,
  "skin": false,
  "hair": false,
  "downloads": 0,
  "categories": [
    "chronological device",
    "chronological instrument"
  ],
  "synsets": [
    "03915635-n",
    "03050242-n"
  ],
  "tags": [
    "object",
    "appliance",
    "time",
    "chronological device"
  ],
  "_id": 5561,
  "created": "2008-09-11T13:41:50.000Z",
  "lastUpdated": "2021-04-23T21:49:20.672Z",
  "keywords": [
    {
      "type": 2,
      "hasLocution": false,
      "keyword": "pendule",
      "plural": "pendule"
    },
    {
      "keyword": "horloge",
      "hasLocution": false,
      "type": 2,
      "plural": "horloge"
    },
    {
      "keyword": "pendule à balancier",
      "hasLocution": false,
      "plural": "pendules à balancier",
      "type": 2
    }
  ],
  "desc": ""
}