{
  "schematic": false,
  "sex": false,
  "violence": false,
  "aac": false,
  "aacColor": false,
  "skin": true,
  "hair": true,
  "downloads": 0,
  "categories": [
    "marital status",
    "wedding",
    "event",
    "religious event",
    "social event"
  ],
  "synsets": [
    "08005815-n",
    "13987306-n",
    "01039028-n"
  ],
  "tags": [
    "person",
    "marital status",
    "event",
    "social event",
    "wedding",
    "religious event"
  ],
  "_id": 8256,
  "created": "2009-02-20T20:32:44.000Z",
  "lastUpdated": "2024-12-13T06:39:05.229Z",
  "keywords": [
    {
      "type": 2,
      "keyword": "mariage",
      "hasLocution": true
    },
    {
      "keyword": "mariés",
      "hasLocution": false,
      "type": 2
    },
    {
      "keyword": "jeunes mariés",
      "hasLocution": false
    }
  ],
  "desc": ""
}