{
  "schematic": false,
  "sex": false,
  "violence": false,
  "aac": false,
  "aacColor": false,
  "skin": true,
  "hair": false,
  "downloads": 0,
  "categories": [
    "verb",
    "animal physiology",
    "insect",
    "animal behaviour"
  ],
  "synsets": [
    "01448026-v"
  ],
  "tags": [
    "communication",
    "language",
    "verb",
    "animal",
    "animal physiology",
    "invertebrate",
    "arthropod",
    "insect",
    "animal behavior"
  ],
  "_id": 8665,
  "created": "2009-05-27T13:08:47.000Z",
  "lastUpdated": "2021-07-19T07:18:27.809Z",
  "keywords": [
    {
      "type": 3,
      "keyword": "piquer",
      "hasLocution": true
    }
  ],
  "desc": ""
}