{
  "schematic": false,
  "sex": false,
  "violence": false,
  "aac": false,
  "aacColor": false,
  "skin": true,
  "hair": false,
  "downloads": 0,
  "categories": [
    "verb",
    "disruptive behavior"
  ],
  "synsets": [
    "00335806-v",
    "01569486-v"
  ],
  "tags": [
    "communication",
    "language",
    "verb",
    "psychology",
    "disruptive behavior"
  ],
  "_id": 9032,
  "created": "2009-08-03T16:11:40.000Z",
  "lastUpdated": "2021-07-19T07:56:05.337Z",
  "keywords": [
    {
      "type": 3,
      "meaning": "tr. Mettre quelque chose en morceaux par choc, par pression, le briser",
      "keyword": "casser",
      "hasLocution": true
    },
    {
      "keyword": "briser",
      "type": 3,
      "hasLocution": false
    }
  ],
  "desc": ""
}