{
  "schematic": false,
  "sex": false,
  "violence": false,
  "aac": false,
  "aacColor": false,
  "skin": true,
  "hair": false,
  "downloads": 0,
  "categories": [
    "verb",
    "work tool",
    "clothing industry"
  ],
  "synsets": [
    "01677786-v",
    "01674934-v"
  ],
  "tags": [
    "communication",
    "language",
    "verb",
    "work",
    "tool",
    "secondary sector",
    "clothing industry"
  ],
  "_id": 9040,
  "created": "2009-08-03T16:29:43.000Z",
  "lastUpdated": "2021-05-07T21:08:57.576Z",
  "keywords": [
    {
      "type": 3,
      "keyword": "tricoter",
      "hasLocution": true
    },
    {
      "keyword": "faire du tricot",
      "hasLocution": false,
      "type": 3
    }
  ],
  "desc": ""
}