{
  "schematic": false,
  "sex": false,
  "violence": false,
  "aac": false,
  "aacColor": false,
  "skin": true,
  "hair": false,
  "downloads": 0,
  "categories": [
    "professional",
    "security and defense"
  ],
  "synsets": [
    "10028930-n"
  ],
  "tags": [
    "work",
    "professional",
    "tertiary sector",
    "defense",
    "security"
  ],
  "_id": 9191,
  "created": "2009-08-04T14:00:02.000Z",
  "lastUpdated": "2021-07-19T10:05:32.547Z",
  "keywords": [
    {
      "type": 2,
      "keyword": "détective",
      "hasLocution": true,
      "plural": "détectives"
    }
  ],
  "desc": ""
}